README.md
setup.py
broadscope_bailian/__init__.py
broadscope_bailian.egg-info/PKG-INFO
broadscope_bailian.egg-info/SOURCES.txt
broadscope_bailian.egg-info/dependency_links.txt
broadscope_bailian.egg-info/requires.txt
broadscope_bailian.egg-info/top_level.txt
broadscope_bailian/api/__init__.py
broadscope_bailian/api/access_token_client.py
broadscope_bailian/api/base_completions.py
broadscope_bailian/api/completions.py
broadscope_bailian/api/models.py
broadscope_bailian/api/util.py