Metadata-Version: 1.2
Name: broadscope-bailian
Version: 1.3.0
Summary: Alibaba Cloud Broadscope BaiLian SDK for Python
Home-page: https://bailian.console.aliyun.com/
Author: Alibaba Cloud SDK
Author-email: sdk-team@alibabacloud.com
License: MIT License
Keywords: alibabacloud,broadscope-bailian
Platform: any
Classifier: Intended Audience :: Developers
Classifier: Natural Language :: English
Classifier: License :: OSI Approved :: MIT License
Classifier: Programming Language :: Python :: 3.7
Classifier: Programming Language :: Python :: 3.8
Classifier: Programming Language :: Python :: 3.9
Classifier: Programming Language :: Python :: 3.10
Requires-Python: >=3.7
